operatorsdavi/__init__.py
operatorsdavi/add.py
operatorsdavi/subtract.py
operatorsdavi-0.0.1.dist-info/LICENSE
operatorsdavi-0.0.1.dist-info/METADATA
operatorsdavi-0.0.1.dist-info/WHEEL
operatorsdavi-0.0.1.dist-info/top_level.txt
operatorsdavi-0.0.1.dist-info/RECORD
