Metadata-Version: 2.1
Name: operatorsdavi
Version: 0.0.1
Summary: MEU PRIMEIRO PACOTE EM PYTHON
Author: davizetinha
Author-email: davi512018@gmail.com
Classifier: Development Status :: 3 - Alpha
Classifier: Intended Audience :: Education
Classifier: Programming Language :: Python :: 3
Classifier: Operating System :: OS Independent
License-File: LICENSE
